{
  "DATA_SET_NAMES": [
    "adressa",
	"cds-and-vinyl",
	"ciaodvd",
	"citeulike-a",
	"cosmetics-shop",
	"globo",
	"gowalla",
	"hetrec-lastfm",
	"jester3",
	"ml-1m",
	"ml-100k",
	"movietweetings",
	"musical-instruments",
    "nowplaying",
	"retailrocket",
	"sketchfab",
	"spotify-playlists",
	"video-games",
	"yelp",
	"yoochoose"
  ],
  "NUM_FOLDS": 5,
  "RECOMMENDERS": [
    "implicit-mf",
    "user-knn",
    "item-knn",
    "alternating-least-squares",
    "bayesian-personalized-ranking",
    "logistic-mf",
    "item-item-cosine",
    "item-item-tfidf",
    "item-item-bm25",
    "random",
    "popularity"
  ],
  "METRICS": [
    "precision",
    "ndcg"
  ],
  "TOPN_SCORE": 5,
  "HPO_TIME_LIMIT": 120,
  "TOPN_SAMPLE": 10,
  "NUM_BATCHES": 10,
  "SCORING_JOBS": 5,
  "JOB_FAIL_EMAIL": "",
  "STAGE0_PRUNING_TIME": "00:15:00",
  "STAGE0_PRUNING_MEMORY": "32G",
  "STAGE0_PRUNING_CORES": 1,
  "STAGE1_SPLITTING_TIME": "01:00:00",
  "STAGE1_SPLITTING_MEMORY": "32G",
  "STAGE1_SPLITTING_CORES": 1,
  "STAGE2_FITTING_TIME": "06:00:00",
  "STAGE2_FITTING_MEMORY": "230G",
  "STAGE2_FITTING_CORES": 1,
  "STAGE3_PREDICTING_TIME": "06:00:00",
  "STAGE3_PREDICTING_MEMORY": "230G",
  "STAGE3_PREDICTING_CORES": 1,
  "STAGE4_SCORING_TIME": "06:00:00",
  "STAGE4_SCORING_MEMORY": "230G",
  "STAGE4_SCORING_CORES": 8,
  "STAGE5_FUSING_TIME": "01:00:00",
  "STAGE5_FUSING_MEMORY": "32G",
  "STAGE5_FUSING_CORES": 1,
  "STAGE6_PLOTTING_TIME": "01:00:00",
  "STAGE6_PLOTTING_MEMORY": "32G",
  "STAGE6_PLOTTING_CORES": 1
}